MANIFEST.in
README.txt
setup.py
mdemos/__init__.py
mdemos.feeds.egg-info/PKG-INFO
mdemos.feeds.egg-info/SOURCES.txt
mdemos.feeds.egg-info/dependency_links.txt
mdemos.feeds.egg-info/entry_points.txt
mdemos.feeds.egg-info/namespace_packages.txt
mdemos.feeds.egg-info/not-zip-safe
mdemos.feeds.egg-info/requires.txt
mdemos.feeds.egg-info/top_level.txt
mdemos/feeds/__init__.py
mdemos/feeds/consumer.py
mdemos/feeds/streams.py
mdemos/feeds/controllers/__init__.py
mdemos/feeds/controllers/root.py
mdemos/feeds/templates/__init__.py
mdemos/feeds/templates/index.mak
mdemos/feeds/widgets/__init__.py
mdemos/feeds/widgets/widgets.py
mdemos/feeds/widgets/static/hgrabber.gif
mdemos/feeds/widgets/static/jquery.cookie.js
mdemos/feeds/widgets/static/main.css
mdemos/feeds/widgets/static/splitter-1.5.js
mdemos/feeds/widgets/static/splitter.js
mdemos/feeds/widgets/static/vdockbar.gif
mdemos/feeds/widgets/static/vgrabber.gif
mdemos/feeds/widgets/static/vgrabber2-active.gif
mdemos/feeds/widgets/static/vgrabber2-normal.gif
mdemos/feeds/widgets/templates/__init__.py
mdemos/feeds/widgets/templates/feedreader.mak