Metadata-Version: 1.0
Name: mdemos.feeds
Version: 0.1.1a
Summary: Moksha Feeds App
Home-page: http://moksha.fedorahosted.org
Author: Luke Macken
Author-email: lmacken@redhat.com
License: ASL 2.0
Platform: UNKNOWN
